{
  "cities": [
    {
      "cityName": "San Juan",
      "country": "Puerto Rico",
      "emoji": "🇵🇷",
      "date": "2027-10-31T15:59:59.138Z",
      "notes": "My favorite city so far!",
      "position": {
        "lat": 18.22935133838668,
        "lng": -66.35742187500001
      },
      "id": "73930385"
    },
    {
      "id": "f137",
      "cityName": "Villa Altagracia",
      "country": "Dominican Republic (the)",
      "emoji": "🇩🇴",
      "date": "2024-04-08T19:34:24.389Z",
      "notes": "f",
      "position": {
        "lat": "18.750309813140653",
        "lng": "-70.29052734375001"
      }
    },
    {
      "id": "ec2a",
      "cityName": "Fantino",
      "country": "Dominican Republic (the)",
      "emoji": "🇩🇴",
      "date": "2024-04-08T19:34:36.254Z",
      "notes": "Hated it. ",
      "position": {
        "lat": "19.072501451715087",
        "lng": "-70.33996582031251"
      }
    },
    {
      "id": "2b44",
      "cityName": "Flagstaff",
      "country": "United States of America (the)",
      "emoji": "🇺🇸",
      "date": "2024-04-09T15:07:24.991Z",
      "notes": "Placed sucked ass.",
      "position": {
        "lat": "35.33529320309331",
        "lng": "-111.719970703125"
      }
    }
  ]
}